typeforce/__init__.py
typeforce/enforcing.py
enforce_typehints-0.0.2.dist-info/LICENSE.txt
enforce_typehints-0.0.2.dist-info/METADATA
enforce_typehints-0.0.2.dist-info/WHEEL
enforce_typehints-0.0.2.dist-info/top_level.txt
enforce_typehints-0.0.2.dist-info/RECORD
