Metadata-Version: 2.1
Name: enforce-typehints
Version: 0.0.2
Summary: Enforce type hints at import time
Home-page: https://github.com/Spindel/enforce_typehints
Author: Spindel Ljungmark
Author-email: spider@skuggor.se
License: UNKNOWN
Platform: UNKNOWN
Classifier: Programming Language :: Python :: 3
Classifier: License :: OSI Approved :: MIT License
Classifier: Operating System :: OS Independent
License-File: LICENSE.txt
Requires-Dist: mypy
